LICENSE
MANIFEST.in
README.md
VERSION
setup.py
data/leaderboards/20201004
data/leaderboards/20201215
data/saves/empty-savegame.sav
data/saves/mostly-full-savegame.sav
docs/leaderboards-format.md
docs/save-format.md
src/s2_data/__init__.py
src/s2_data/journal_entries.py
src/s2_data/leaderboards.py
src/s2_data.egg-info/PKG-INFO
src/s2_data.egg-info/SOURCES.txt
src/s2_data.egg-info/dependency_links.txt
src/s2_data.egg-info/entry_points.txt
src/s2_data.egg-info/requires.txt
src/s2_data.egg-info/top_level.txt
src/s2_data/saves/__init__.py
src/s2_data/saves/cli.py
src/s2_data/saves/field_descriptors.py
src/s2_data/saves/field_types.py
src/tests/__init__.py
src/tests/test_descriptors.py