Metadata-Version: 2.1
Name: s2-data
Version: 0.25
Summary: Spelunky 2 Data Utilities.
Home-page: UNKNOWN
License: UNKNOWN
Keywords: games
Platform: UNKNOWN
Classifier: Development Status :: 3 - Alpha
Classifier: Intended Audience :: Other Audience
Classifier: License :: OSI Approved :: Apache Software License
Classifier: Programming Language :: Python :: 3
Classifier: Programming Language :: Python :: 3.7
Classifier: Programming Language :: Python :: 3.8
Classifier: Programming Language :: Python :: 3 :: Only
Requires-Python: >=3.7, <4
